django_deno/__init__.py
django_deno/commands.py
django_deno/dir.py
django_deno/handlers.py
django_deno/importmap.py
django_deno/itero.py
django_deno/regex.py
django_deno/sourcefile.py
django_deno/utils.py
django_deno/views.py
django_deno/api/deno.py
django_deno/api/json.py
django_deno/api/maps.py
django_deno/api/rollup.py
django_deno/conf/settings.py
django_deno/deno/deno.json
django_deno/deno/deno.lock
django_deno/deno/deno_sucrase.json
django_deno/deno/deno_sucrase.lock
django_deno/deno/deno_swc.json
django_deno/deno/deno_swc.lock
django_deno/deno/django_deno.Linux.x86_64.hash
django_deno/deno/django_deno.Windows.AMD64.hash
django_deno/deno/django_deno.log
django_deno/deno/import_map.json
django_deno/deno/importmap.ts
django_deno/deno/localpath.ts
django_deno/deno/lock.json
django_deno/deno/no_resolve.ts
django_deno/deno/no_sucrase.ts
django_deno/deno/no_swc.ts
django_deno/deno/no_terser.ts
django_deno/deno/rollup.rst
django_deno/deno/rollup.ts
django_deno/deno/server.ts
django_deno/deno/.vscode/launch.json
django_deno/deno/.vscode/settings.json
django_deno/deno/resolver/ensureUrl.ts
django_deno/deno/resolver/error.ts
django_deno/deno/resolver/exists.ts
django_deno/deno/resolver/getUrlBase.ts
django_deno/deno/resolver/handleUnresolvedId.ts
django_deno/deno/resolver/isTypescript.ts
django_deno/deno/resolver/loadUrl.ts
django_deno/deno/resolver/logging.ts
django_deno/deno/resolver/notImplemented.ts
django_deno/deno/resolver/parse.ts
django_deno/deno/resolver/relativeId.ts
django_deno/deno/resolver/resolveId.ts
django_deno/deno/vendor/import_map.json
django_deno/deno/vendor/cdn.esm.sh/v43/node_process.js
django_deno/deno/vendor/cdn.esm.sh/v43/ms@2.1.3/deno/ms.js
django_deno/deno/vendor/cdn.esm.sh/v43/path-browserify@1.0.1/deno/path-browserify.js
django_deno/deno/vendor/cdn.esm.sh/v43/picomatch@2.3.0/deno/picomatch.js
django_deno/deno/vendor/deno.land/std@0.108.0/fmt/colors.ts
django_deno/deno/vendor/deno.land/std@0.110.0/_util/assert.ts
django_deno-0.2.0.dist-info/LICENSE
django_deno-0.2.0.dist-info/METADATA
django_deno-0.2.0.dist-info/WHEEL
django_deno-0.2.0.dist-info/top_level.txt
django_deno-0.2.0.dist-info/RECORD
