Metadata-Version: 2.1
Name: django-deno
Version: 0.2.0
Summary: Deno front-end integration for Django
Home-page: https://github.com/Dmitri-Sintsov/django-deno
Author: Dmitriy Sintsov
Author-email: questpc256@gmail.com
License: LGPL-3.0
Keywords: django,deno,rollup,swc,sucrase,typescript,runserver,collectstatic
Classifier: Development Status :: 4 - Beta
Classifier: Environment :: Web Environment
Classifier: Framework :: Django
Classifier: Intended Audience :: Developers
Classifier: License :: OSI Approved :: GNU Lesser General Public License v2 or later (LGPLv2+)
Classifier: Operating System :: OS Independent
Classifier: Programming Language :: Python :: 3
Classifier: Topic :: Internet :: WWW/HTTP :: Dynamic Content
License-File: LICENSE
Requires-Dist: Django
Requires-Dist: jsonschema
Requires-Dist: ijson
Requires-Dist: requests
Requires-Dist: psutil
